zipkin_agent/__init__.py
zipkin_agent/config.py
zipkin_agent/decorators.py
zipkin_agent/loggings.py
zipkin_agent/setup.py
zipkin_agent/agent/__init__.py
zipkin_agent/build/__init__.py
zipkin_agent/build/lib/__init__.py
zipkin_agent/build/lib/agent/__init__.py
zipkin_agent/build/lib/plugins/__init__.py
zipkin_agent/build/lib/plugins/sw_flask.py
zipkin_agent/build/lib/plugins/sw_requests.py
zipkin_agent/build/lib/trace/__init__.py
zipkin_agent/build/lib/trace/tags.py
zipkin_agent/build/lib/utils/__init__.py
zipkin_agent/build/lib/utils/counter.py
zipkin_agent/build/lib/utils/lang.py
zipkin_agent/plugins/__init__.py
zipkin_agent/plugins/trace_dapr.py
zipkin_agent/plugins/trace_flask.py
zipkin_agent/plugins/trace_requests.py
zipkin_agent/test/__init__.py
zipkin_agent/test/services/__init__.py
zipkin_agent/test/services/consumer.py
zipkin_agent/test/services/provider.py
zipkin_agent/trace/__init__.py
zipkin_agent/trace/tags.py
zipkin_agent/utils/__init__.py
zipkin_agent/utils/counter.py
zipkin_agent/utils/lang.py
zipkin_agent-0.1.1.dist-info/METADATA
zipkin_agent-0.1.1.dist-info/WHEEL
zipkin_agent-0.1.1.dist-info/top_level.txt
zipkin_agent-0.1.1.dist-info/RECORD
