Metadata-Version: 2.1
Name: zipkin-agent
Version: 0.1.1
Summary: Python Agent for zipkin-agent
Home-page: https://github.com/apache/skywalking-python/
Author: Apache
Author-email: dev@skywalking.apache.org
License: Apache 2.0
Platform: UNKNOWN
Classifier: Framework :: Flake8
Classifier: License :: OSI Approved :: Apache Software License
Classifier: Operating System :: OS Independent
Classifier: Programming Language :: Python
Classifier: Programming Language :: Python :: 3
Classifier: Programming Language :: Python :: 3.5
Classifier: Programming Language :: Python :: 3.6
Classifier: Programming Language :: Python :: 3.7
Classifier: Programming Language :: Python :: 3.8
Classifier: Programming Language :: Python :: 3.9
Classifier: Topic :: Software Development
Requires-Dist: packaging
Requires-Dist: wrapt
Provides-Extra: http
Requires-Dist: requests (>=2.26.0) ; extra == 'http'
Requires-Dist: dapr (>=1.4.0) ; extra == 'http'
Requires-Dist: dapr-ext-grpc (>=1.4.0) ; extra == 'http'
Requires-Dist: Flask (>=2.0.2) ; extra == 'http'
Provides-Extra: test
Requires-Dist: testcontainers ; extra == 'test'
Requires-Dist: pyyaml ; extra == 'test'
Requires-Dist: pytest ; extra == 'test'
